{
    "summary": [
        "The sort script handles toggling of classes.",
        "You choose to either toggle everything inside <code>js-toggle-multi</code> container",
        "or by adding <code>js-toggle-single</code> to any element. The data attribute value is the class that you toggle."
    ],
    "description": {
        "data-js-toggle-container": "Outer container",
        "data-js-toggle-single": "A single element to toggle",
        "data-js-toggle-multi": "A container where every child is toggled",
        "data-js-toggle-trigger": "An element with a click event attached to toggle"
    },
    "attributes": {
        "data-js-toggle-container": "",
        "data-js-toggle-single": "class",
        "data-js-toggle-multi": "class",
        "data-js-toggle-trigger": ""
    }
}